test_vert/__init__.py
test_vert/test_stores/__init__.py
test_vert/test_stores/_base.py
test_vert/test_stores/test_dbm.py
test_vert/test_stores/test_memory.py
vert/__about__.py
vert/__init__.py
vert/graphs.py
vert/stores/__init__.py
vert/stores/base.py
vert/stores/dbm.py
vert/stores/memory.py
vert-1.0.1.dist-info/DESCRIPTION.rst
vert-1.0.1.dist-info/METADATA
vert-1.0.1.dist-info/RECORD
vert-1.0.1.dist-info/WHEEL
vert-1.0.1.dist-info/metadata.json
vert-1.0.1.dist-info/top_level.txt
