Metadata-Version: 2.0
Name: vert
Version: 1.0.1
Summary: Universal Graph Interface for Python
Home-page: https://pypi.python.org/pypi/vert
Author: Aaron M. Hosford
Author-email: hosford42@gmail.com
License: MIT
Keywords: graph vertex edge node link network semantic database
Platform: UNKNOWN
Classifier: Development Status :: 4 - Beta
Classifier: License :: OSI Approved :: MIT License
Classifier: Programming Language :: Python :: 3.5
Classifier: Programming Language :: Python :: 3.6
Classifier: Programming Language :: Python :: 3 :: Only
Classifier: Topic :: Database :: Front-Ends
Classifier: Topic :: Scientific/Engineering :: Information Analysis
Classifier: Topic :: Scientific/Engineering :: Interface Engine/Protocol Translator
Classifier: Topic :: Scientific/Engineering :: Mathematics
